ocp_scale_utilities/__init__.py
ocp_scale_utilities/constants.py
ocp_scale_utilities/logger.py
ocp_scale_utilities/monitoring.py
ocp_scale_utilities/threaded/__init__.py
ocp_scale_utilities/threaded/scale.py
ocp_scale_utilities/threaded/utils.py
openshift_python_scale_utilities-0.1.1.5.dist-info/METADATA
openshift_python_scale_utilities-0.1.1.5.dist-info/WHEEL
openshift_python_scale_utilities-0.1.1.5.dist-info/licenses/LICENSE
openshift_python_scale_utilities-0.1.1.5.dist-info/RECORD
