Metadata-Version: 2.4
Name: openshift-python-scale-utilities
Version: 0.1.1.5
Summary: OpenShift Python Scale Utilities
Project-URL: homepage, https://github.com/redhat-vmeperf/openshift-python-scale-utilities
Project-URL: Download, https://pypi.org/project/openshift-python-scale-utilities/
Project-URL: Bug Tracker, https://github.com/redhat-vmeperf/openshift-python-scale-utilities/issues
Author-email: Sarah Bennert <sarahbx@redhat.com>
Maintainer-email: Sarah Bennert <sarahbx@redhat.com>
License-Expression: Apache-2.0
License-File: LICENSE
Keywords: Kubevirt,Openshift,Openshift Virtualization
Classifier: Operating System :: OS Independent
Classifier: Programming Language :: Python :: 3
Requires-Python: >=3.12.0
Requires-Dist: openshift-python-utilities>=6.0.0
Requires-Dist: openshift-python-wrapper>=11.0.44
Requires-Dist: pytest-order>=1.3.0
Requires-Dist: pytest>=8.3.3
Requires-Dist: python-simple-logger~=2.0.9
Requires-Dist: timeout-sampler>=1.0.1
